rawa_bots/__init__.py
rawa_bots/bot.py
rawa_bots/exceptions.py
rawa_bots/gemini_bot.py
rawa_bots/openai_bot.py
rawa_bots-0.2.5.dist-info/licenses/LICENSE
rawa_bots-0.2.5.dist-info/METADATA
rawa_bots-0.2.5.dist-info/WHEEL
rawa_bots-0.2.5.dist-info/top_level.txt
rawa_bots-0.2.5.dist-info/RECORD
