Metadata-Version: 2.4
Name: rawa_bots
Version: 0.2.5
Summary: A Python library to easily build Gemini-powered chatbots and generate images.
Author: Your Name or Organization
Author-email: Your Name or Organization <your@email.com>
License: MIT License
Requires-Python: >=3.8
License-File: LICENSE
Requires-Dist: requests
Requires-Dist: Pillow
Dynamic: author
Dynamic: license-file
Dynamic: requires-python
